setup.py
odoo/addons/mail_cc_and_to_text/CHANGELOG.md
odoo/addons/mail_cc_and_to_text/README.rst
odoo/addons/mail_cc_and_to_text/__init__.py
odoo/addons/mail_cc_and_to_text/__manifest__.py
odoo/addons/mail_cc_and_to_text/models/__init__.py
odoo/addons/mail_cc_and_to_text/models/helpdesk_ticket.py
odoo/addons/mail_cc_and_to_text/models/mail_message.py
odoo/addons/mail_cc_and_to_text/models/mail_thread.py
odoo/addons/mail_cc_and_to_text/static/description/icon.png
odoo/addons/mail_cc_and_to_text/wizard/__init__.py
odoo/addons/mail_cc_and_to_text/wizard/mail_compose_message.py
odoo/addons/mail_cc_and_to_text/wizard/mail_compose_message_view.xml
odoo_addon_mail_cc_and_to_text.egg-info/PKG-INFO
odoo_addon_mail_cc_and_to_text.egg-info/SOURCES.txt
odoo_addon_mail_cc_and_to_text.egg-info/dependency_links.txt
odoo_addon_mail_cc_and_to_text.egg-info/not-zip-safe
odoo_addon_mail_cc_and_to_text.egg-info/requires.txt
odoo_addon_mail_cc_and_to_text.egg-info/top_level.txt